qiipy/__init__.py
qiipy/_api.py
qiipy/_models.py
qiipy-0.1.0.dist-info/LICENSE
qiipy-0.1.0.dist-info/WHEEL
qiipy-0.1.0.dist-info/METADATA
qiipy-0.1.0.dist-info/RECORD
