Metadata-Version: 2.1
Name: qiipy
Version: 0.1.0
Summary: 
Author: sh1ma
Author-email: in9lude@gmail.com
Requires-Python: >=3.8,<4.0
Classifier: Programming Language :: Python :: 3
Classifier: Programming Language :: Python :: 3.8
Requires-Dist: apywrapper (>=0.1.4,<0.2.0)
